<?xml version="1.0" encoding="ISO-8859-1" standalone="no" ?>
<ApplicationData>
  <Application AID="A0000000031010" KernelID="030000">
    <ASI_DFAB02>01</ASI_DFAB02>
    <AppFlowCap_DFAB03>0C03000000</AppFlowCap_DFAB03>
    <SpecialTRXConfig_DFAB05>2120110000000000</SpecialTRXConfig_DFAB05>
    <ChksumEntryPoint_DFAB06>8907D85E</ChksumEntryPoint_DFAB06>
    <ChksumKernel_DFAB07></ChksumKernel_DFAB07>
    <RetapFieldOff_DFAB08>0A</RetapFieldOff_DFAB08>
    <AdditionalTagsTRM_DFAB20></AdditionalTagsTRM_DFAB20>
    <AdditionalTagsCRD_DFAB21></AdditionalTagsCRD_DFAB21>
    <DefaultApplicationName_DFAB22>VISA</DefaultApplicationName_DFAB22>
    <Visa>
      <TermIdent_9F1C>3132333435363738</TermIdent_9F1C>
      <TerminalCountryCode_9F1A>0840</TerminalCountryCode_9F1A>
      <TerminalType_9F35>22</TerminalType_9F35>
      <TerminalTransactionQualifier_9F66>36204000</TerminalTransactionQualifier_9F66>
      <TerminalCapabilities_9F33>E0F8C8</TerminalCapabilities_9F33>
      <AdditionalTerminalCapabilities_9F40>F000F0A001</AdditionalTerminalCapabilities_9F40>
      <VersionNumber_9F09>008D000000000000000000000000000000000000</VersionNumber_9F09>
      <MerchantCategoryCode_9F15>5999</MerchantCategoryCode_9F15>
      <MerchantIdentifier_9F16/>
      <MerchantNameAndLocation_9F4E></MerchantNameAndLocation_9F4E>
      <TecSupport_DFAB30>01</TecSupport_DFAB30>
      <AppFlowCap_DFAB31>0A00000000</AppFlowCap_DFAB31>
      <ContactlessFloorLimit_DFAB40>000000000000</ContactlessFloorLimit_DFAB40>
      <ContactlessTransactionLimit_DFAB41>000000002500</ContactlessTransactionLimit_DFAB41>
      <ContactlessCVMRequiredLimit_DFAB42>000000001000</ContactlessCVMRequiredLimit_DFAB42>
      <VisaDRLParams_FFAB01>
        <AppProgramId_9F5A>3102682620</AppProgramId_9F5A>
        <ContactlessFloorLimit_DFAB40>000000000000</ContactlessFloorLimit_DFAB40>
        <ContactlessTransactionLimit_DFAB41>000000999999</ContactlessTransactionLimit_DFAB41>
        <ContactlessCVMRequiredLimit_DFAB42>000000003001</ContactlessCVMRequiredLimit_DFAB42>
        <OnOffSwitch_DFAB49>00</OnOffSwitch_DFAB49></VisaDRLParams_FFAB01>
      <VisaDRLParams_FFAB01>
        <AppProgramId_9F5A>3102682612000003</AppProgramId_9F5A>
        <ContactlessFloorLimit_DFAB40>000000000000</ContactlessFloorLimit_DFAB40>
        <ContactlessTransactionLimit_DFAB41>000000999999</ContactlessTransactionLimit_DFAB41>
        <ContactlessCVMRequiredLimit_DFAB42>000000001501</ContactlessCVMRequiredLimit_DFAB42>
        <OnOffSwitch_DFAB49>01</OnOffSwitch_DFAB49></VisaDRLParams_FFAB01>
      <VisaDRLParams_FFAB01>
        <AppProgramId_9F5A>3102682612</AppProgramId_9F5A>
        <ContactlessFloorLimit_DFAB40>000000000000</ContactlessFloorLimit_DFAB40>
        <ContactlessTransactionLimit_DFAB41>000000999999</ContactlessTransactionLimit_DFAB41>
        <ContactlessCVMRequiredLimit_DFAB42>000000001501</ContactlessCVMRequiredLimit_DFAB42>
        <OnOffSwitch_DFAB49>02</OnOffSwitch_DFAB49></VisaDRLParams_FFAB01>
      <VisaDRLParams_FFAB01>
        <AppProgramId_9F5A>3102682600</AppProgramId_9F5A>
        <ContactlessFloorLimit_DFAB40>000000000000</ContactlessFloorLimit_DFAB40>
        <ContactlessTransactionLimit_DFAB41>000000999999</ContactlessTransactionLimit_DFAB41>
        <ContactlessCVMRequiredLimit_DFAB42>000000002001</ContactlessCVMRequiredLimit_DFAB42>
        <OnOffSwitch_DFAB49>03</OnOffSwitch_DFAB49></VisaDRLParams_FFAB01></Visa></Application>
  <Application AID="A0000000980840" KernelID="030000">
    <ASI_DFAB02>01</ASI_DFAB02>
    <AppFlowCap_DFAB03>0000000000</AppFlowCap_DFAB03>
    <SpecialTRXConfig_DFAB05>2120110000000000</SpecialTRXConfig_DFAB05>
    <ChksumEntryPoint_DFAB06>8907D85E</ChksumEntryPoint_DFAB06>
    <ChksumKernel_DFAB07></ChksumKernel_DFAB07>
    <RetapFieldOff_DFAB08>0D</RetapFieldOff_DFAB08>
    <AdditionalTagsTRM_DFAB20></AdditionalTagsTRM_DFAB20>
    <AdditionalTagsCRD_DFAB21>4203</AdditionalTagsCRD_DFAB21>
    <DefaultApplicationName_DFAB22>Visa</DefaultApplicationName_DFAB22>
    <Visa>
      <TermIdent_9F1C>3132333435363738</TermIdent_9F1C>
      <TerminalCountryCode_9F1A>0840</TerminalCountryCode_9F1A>
      <TerminalType_9F35>22</TerminalType_9F35>
      <TerminalTransactionQualifier_9F66>36204000</TerminalTransactionQualifier_9F66>
      <TerminalCapabilities_9F33>E068C8</TerminalCapabilities_9F33>
      <AdditionalTerminalCapabilities_9F40>F000F0A001</AdditionalTerminalCapabilities_9F40>
      <VersionNumber_9F09>0096000000000000000000000000000000000000</VersionNumber_9F09>
      <MerchantCategoryCode_9F15>5999</MerchantCategoryCode_9F15>
      <MerchantIdentifier_9F16/>
      <MerchantNameAndLocation_9F4E></MerchantNameAndLocation_9F4E>
      <TecSupport_DFAB30>01</TecSupport_DFAB30>
      <AppFlowCap_DFAB31>0400000000</AppFlowCap_DFAB31>
      <ContactlessFloorLimit_DFAB40>000000000000</ContactlessFloorLimit_DFAB40>
      <ContactlessTransactionLimit_DFAB41>000099999999</ContactlessTransactionLimit_DFAB41>
      <ContactlessCVMRequiredLimit_DFAB42>000000000000</ContactlessCVMRequiredLimit_DFAB42></Visa></Application>
  <Application AID="A0000000032010" KernelID="030000">
    <ASI_DFAB02>01</ASI_DFAB02>
    <AppFlowCap_DFAB03>0C03000000</AppFlowCap_DFAB03>
    <SpecialTRXConfig_DFAB05>2120110000000000</SpecialTRXConfig_DFAB05>
    <ChksumEntryPoint_DFAB06>8907D85E</ChksumEntryPoint_DFAB06>
    <ChksumKernel_DFAB07></ChksumKernel_DFAB07>
    <RetapFieldOff_DFAB08>0A</RetapFieldOff_DFAB08>
    <AdditionalTagsTRM_DFAB20></AdditionalTagsTRM_DFAB20>
    <AdditionalTagsCRD_DFAB21></AdditionalTagsCRD_DFAB21>
    <DefaultApplicationName_DFAB22>Visa Electron</DefaultApplicationName_DFAB22>
    <Visa>
      <TermIdent_9F1C>3132333435363738</TermIdent_9F1C>
      <TerminalCountryCode_9F1A>0840</TerminalCountryCode_9F1A>
      <TerminalType_9F35>22</TerminalType_9F35>
      <TerminalTransactionQualifier_9F66>36204000</TerminalTransactionQualifier_9F66>
      <TerminalCapabilities_9F33>E0F8C8</TerminalCapabilities_9F33>
      <AdditionalTerminalCapabilities_9F40>F000F0A001</AdditionalTerminalCapabilities_9F40>
      <VersionNumber_9F09>008D000000000000000000000000000000000000</VersionNumber_9F09>
      <MerchantCategoryCode_9F15>5999</MerchantCategoryCode_9F15>
      <MerchantIdentifier_9F16/>
      <MerchantNameAndLocation_9F4E></MerchantNameAndLocation_9F4E>
      <TecSupport_DFAB30>01</TecSupport_DFAB30>
      <AppFlowCap_DFAB31>0400000000</AppFlowCap_DFAB31>
      <ContactlessFloorLimit_DFAB40>000000000000</ContactlessFloorLimit_DFAB40>
      <ContactlessTransactionLimit_DFAB41>000000002001</ContactlessTransactionLimit_DFAB41>
      <ContactlessCVMRequiredLimit_DFAB42>000000000901</ContactlessCVMRequiredLimit_DFAB42></Visa></Application>
  <Application AID="A0000000032020" KernelID="030000">
    <ASI_DFAB02>01</ASI_DFAB02>
    <AppFlowCap_DFAB03>0C03000000</AppFlowCap_DFAB03>
    <SpecialTRXConfig_DFAB05>2120110000000000</SpecialTRXConfig_DFAB05>
    <ChksumEntryPoint_DFAB06>8907D85E</ChksumEntryPoint_DFAB06>
    <ChksumKernel_DFAB07></ChksumKernel_DFAB07>
    <RetapFieldOff_DFAB08>0A</RetapFieldOff_DFAB08>
    <AdditionalTagsTRM_DFAB20></AdditionalTagsTRM_DFAB20>
    <AdditionalTagsCRD_DFAB21></AdditionalTagsCRD_DFAB21>
    <DefaultApplicationName_DFAB22>Visa VPay</DefaultApplicationName_DFAB22>
    <Visa>
      <TermIdent_9F1C>3132333435363738</TermIdent_9F1C>
      <TerminalCountryCode_9F1A>0840</TerminalCountryCode_9F1A>
      <TerminalType_9F35>22</TerminalType_9F35>
      <TerminalTransactionQualifier_9F66>36204000</TerminalTransactionQualifier_9F66>
      <TerminalCapabilities_9F33>E0F8C8</TerminalCapabilities_9F33>
      <AdditionalTerminalCapabilities_9F40>F000F0A001</AdditionalTerminalCapabilities_9F40>
      <VersionNumber_9F09>008C000000000000000000000000000000000000</VersionNumber_9F09>
      <MerchantCategoryCode_9F15>5999</MerchantCategoryCode_9F15>
      <MerchantIdentifier_9F16/>
      <MerchantNameAndLocation_9F4E></MerchantNameAndLocation_9F4E>
      <TecSupport_DFAB30>01</TecSupport_DFAB30>
      <AppFlowCap_DFAB31>0400000000</AppFlowCap_DFAB31>
      <ContactlessFloorLimit_DFAB40>000000000000</ContactlessFloorLimit_DFAB40>
      <ContactlessTransactionLimit_DFAB41>000000002000</ContactlessTransactionLimit_DFAB41>
      <ContactlessCVMRequiredLimit_DFAB42>000000000900</ContactlessCVMRequiredLimit_DFAB42></Visa></Application>
  <Application AID="A0000000033010" KernelID="030000">
    <ASI_DFAB02>01</ASI_DFAB02>
    <AppFlowCap_DFAB03>0200000000</AppFlowCap_DFAB03>
    <SpecialTRXConfig_DFAB05>2120110000000000</SpecialTRXConfig_DFAB05>
    <ChksumEntryPoint_DFAB06>8907D85E</ChksumEntryPoint_DFAB06>
    <ChksumKernel_DFAB07></ChksumKernel_DFAB07>
    <RetapFieldOff_DFAB08>0D</RetapFieldOff_DFAB08>
    <AdditionalTagsTRM_DFAB20></AdditionalTagsTRM_DFAB20>
    <AdditionalTagsCRD_DFAB21>4203</AdditionalTagsCRD_DFAB21>
    <DefaultApplicationName_DFAB22>Visa</DefaultApplicationName_DFAB22>
    <Visa>
      <TermIdent_9F1C>3132333435363738</TermIdent_9F1C>
      <TerminalCountryCode_9F1A>0840</TerminalCountryCode_9F1A>
      <TerminalType_9F35>22</TerminalType_9F35>
      <TerminalTransactionQualifier_9F66>36204000</TerminalTransactionQualifier_9F66>
      <TerminalCapabilities_9F33>E068C8</TerminalCapabilities_9F33>
      <AdditionalTerminalCapabilities_9F40>F000F0A001</AdditionalTerminalCapabilities_9F40>
      <VersionNumber_9F09>0096000000000000000000000000000000000000</VersionNumber_9F09>
      <MerchantCategoryCode_9F15>5999</MerchantCategoryCode_9F15>
      <MerchantIdentifier_9F16/>
      <MerchantNameAndLocation_9F4E></MerchantNameAndLocation_9F4E>
      <TecSupport_DFAB30>01</TecSupport_DFAB30>
      <AppFlowCap_DFAB31>0400000000</AppFlowCap_DFAB31>
      <ContactlessFloorLimit_DFAB40>000000000000</ContactlessFloorLimit_DFAB40>
      <ContactlessTransactionLimit_DFAB41>000099999999</ContactlessTransactionLimit_DFAB41>
      <ContactlessCVMRequiredLimit_DFAB42>000000000000</ContactlessCVMRequiredLimit_DFAB42></Visa></Application>
  <Application AID="A0000000041010" KernelID="020000">
    <ASI_DFAB02>01</ASI_DFAB02>
    <AppFlowCap_DFAB03>0C03000000</AppFlowCap_DFAB03>
    <SpecialTRXConfig_DFAB05>2120110000000000</SpecialTRXConfig_DFAB05>
    <ChksumEntryPoint_DFAB06>8907D85E</ChksumEntryPoint_DFAB06>
    <ChksumKernel_DFAB07></ChksumKernel_DFAB07>
    <RetapFieldOff_DFAB08>0A</RetapFieldOff_DFAB08>
    <AdditionalTagsTRM_DFAB20></AdditionalTagsTRM_DFAB20>
    <AdditionalTagsCRD_DFAB21></AdditionalTagsCRD_DFAB21>
    <DefaultApplicationName_DFAB22>Mastercard</DefaultApplicationName_DFAB22>
    <MasterCard>
      <TermIdent_9F1C>3132333435363738</TermIdent_9F1C>
      <TerminalCountryCode_9F1A>0840</TerminalCountryCode_9F1A>
      <TerminalType_9F35>22</TerminalType_9F35>
      <AdditionalTerminalCapabilities_9F40>F000F0A001</AdditionalTerminalCapabilities_9F40>
      <MagstripeCVM_aboveLimit_DF811E>20</MagstripeCVM_aboveLimit_DF811E>
      <MagstripeCVM_belowLimit_DF812C>00</MagstripeCVM_belowLimit_DF812C>
      <ChipCVM_aboveLimit_DF8118>60</ChipCVM_aboveLimit_DF8118>
      <ChipCVM_belowLimit_DF8119>08</ChipCVM_belowLimit_DF8119>
      <SecurityCapability_DF811F>08</SecurityCapability_DF811F>
      <CardDataInputCapability_DF8117>E0</CardDataInputCapability_DF8117>
      <FloorLimit_DF8123>000000000000</FloorLimit_DF8123>
      <TransactionLimitNoOnDevice_DF8124>000000002500</TransactionLimitNoOnDevice_DF8124>
      <TransactionLimitOnDevice_DF8125>000000200000</TransactionLimitOnDevice_DF8125>
      <CVMRequiredLimit_DF8126>000000001000</CVMRequiredLimit_DF8126>
      <ChipVersionNumber_9F09>0002000000000000000000000000000000000000</ChipVersionNumber_9F09>
      <MSRVersionNumber_9F6D>0001</MSRVersionNumber_9F6D>
      <KernelConfiguration_DF811B>30</KernelConfiguration_DF811B>
      <TransactionCategoryCode_9F53>52</TransactionCategoryCode_9F53>
      <TACDefault_DF8120>FC509C8800</TACDefault_DF8120>
      <TACDenial_DF8121>0000000000</TACDenial_DF8121>
      <TACOnline_DF8122>FC509C8800</TACOnline_DF8122>
      <KernelID_DF810C>02</KernelID_DF810C>
      <TerminalRiskManagementData_9F1D>647A000000000000</TerminalRiskManagementData_9F1D>
      <MerchantCategoryCode_9F15>5999</MerchantCategoryCode_9F15>
      <MerchantIdentifier_9F16/>
      <MerchantNameAndLocation_9F4E></MerchantNameAndLocation_9F4E>
      <AcquirerIdentifier_9F01>000000000000</AcquirerIdentifier_9F01>
      <HoldTimeValue_DF8130>00</HoldTimeValue_DF8130>
      <MessageHoldTime_DF812D>000000</MessageHoldTime_DF812D>
      <TornTransactionLifetime_DF811C>0078</TornTransactionLifetime_DF811C>
      <TornTransactionNumber_DF811D>02</TornTransactionNumber_DF811D>
      <PhoneMessageTable_DF8131>0000000000000000</PhoneMessageTable_DF8131>
      <TagsToRead_DF8112></TagsToRead_DF8112>
      <TagsToWriteBeforeGenAC_FF8102></TagsToWriteBeforeGenAC_FF8102>
      <TagsToWriteAfterGenAC_FF8103></TagsToWriteAfterGenAC_FF8103>
      <ProceedToFirstWriteFlag_DF8110>FE</ProceedToFirstWriteFlag_DF8110>
      <DSRequestedOperatorID_9F5C>FFFFFFFFFFFFFFFF</DSRequestedOperatorID_9F5C>
      <DETimeoutValue_DF8127>01F4</DETimeoutValue_DF8127>
      <AppFlowCap_DFAB31>0200000000</AppFlowCap_DFAB31>
      <RR_MinGracePeriod_DF8132>0014</RR_MinGracePeriod_DF8132>
      <RR_MaxGracePeriod_DF8133>0032</RR_MaxGracePeriod_DF8133>
      <RR_ExpTransTimeCAPDU_DF8134>0012</RR_ExpTransTimeCAPDU_DF8134>
      <RR_ExpTransTimeRAPDU_DF8135>0018</RR_ExpTransTimeRAPDU_DF8135>
      <RR_AccuracyThreshold_DF8136>012C</RR_AccuracyThreshold_DF8136>
      <RR_TransTimeMismatchThreshold_DF8137>32</RR_TransTimeMismatchThreshold_DF8137>
      <MerchantCustomData_9F7C></MerchantCustomData_9F7C></MasterCard></Application>
  <Application AID="A0000000043060" KernelID="020000">
    <ASI_DFAB02>01</ASI_DFAB02>
    <AppFlowCap_DFAB03>0C03000000</AppFlowCap_DFAB03>
    <SpecialTRXConfig_DFAB05>2120110000000000</SpecialTRXConfig_DFAB05>
    <ChksumEntryPoint_DFAB06>8907D85E</ChksumEntryPoint_DFAB06>
    <ChksumKernel_DFAB07></ChksumKernel_DFAB07>
    <RetapFieldOff_DFAB08>0A</RetapFieldOff_DFAB08>
    <AdditionalTagsTRM_DFAB20></AdditionalTagsTRM_DFAB20>
    <AdditionalTagsCRD_DFAB21></AdditionalTagsCRD_DFAB21>
    <DefaultApplicationName_DFAB22>Maestro</DefaultApplicationName_DFAB22>
    <MasterCard>
      <TermIdent_9F1C>3132333435363738</TermIdent_9F1C>
      <TerminalCountryCode_9F1A>0840</TerminalCountryCode_9F1A>
      <TerminalType_9F35>22</TerminalType_9F35>
      <AdditionalTerminalCapabilities_9F40>F000F0A001</AdditionalTerminalCapabilities_9F40>
      <MagstripeCVM_aboveLimit_DF811E>20</MagstripeCVM_aboveLimit_DF811E>
      <MagstripeCVM_belowLimit_DF812C>00</MagstripeCVM_belowLimit_DF812C>
      <ChipCVM_aboveLimit_DF8118>40</ChipCVM_aboveLimit_DF8118>
      <ChipCVM_belowLimit_DF8119>08</ChipCVM_belowLimit_DF8119>
      <SecurityCapability_DF811F>08</SecurityCapability_DF811F>
      <CardDataInputCapability_DF8117>E0</CardDataInputCapability_DF8117>
      <FloorLimit_DF8123>000000000000</FloorLimit_DF8123>
      <TransactionLimitNoOnDevice_DF8124>000000002500</TransactionLimitNoOnDevice_DF8124>
      <TransactionLimitOnDevice_DF8125>000000200000</TransactionLimitOnDevice_DF8125>
      <CVMRequiredLimit_DF8126>000000001000</CVMRequiredLimit_DF8126>
      <ChipVersionNumber_9F09>0002000000000000000000000000000000000000</ChipVersionNumber_9F09>
      <MSRVersionNumber_9F6D>0001000000000000000000000000000000000000</MSRVersionNumber_9F6D>
      <KernelConfiguration_DF811B>B0</KernelConfiguration_DF811B>
      <TransactionCategoryCode_9F53>52</TransactionCategoryCode_9F53>
      <TACDefault_DF8120>FC501C8800</TACDefault_DF8120>
      <TACDenial_DF8121>0000800000</TACDenial_DF8121>
      <TACOnline_DF8122>FC501C8800</TACOnline_DF8122>
      <KernelID_DF810C>02</KernelID_DF810C>
      <TerminalRiskManagementData_9F1D>647A800000000000</TerminalRiskManagementData_9F1D>
      <MerchantCategoryCode_9F15>5999</MerchantCategoryCode_9F15>
      <MerchantIdentifier_9F16/>
      <MerchantNameAndLocation_9F4E></MerchantNameAndLocation_9F4E>
      <AcquirerIdentifier_9F01>000000000000</AcquirerIdentifier_9F01>
      <HoldTimeValue_DF8130>00</HoldTimeValue_DF8130>
      <MessageHoldTime_DF812D>000000</MessageHoldTime_DF812D>
      <TornTransactionLifetime_DF811C>0078</TornTransactionLifetime_DF811C>
      <TornTransactionNumber_DF811D>02</TornTransactionNumber_DF811D>
      <PhoneMessageTable_DF8131>0000000000000000</PhoneMessageTable_DF8131>
      <TagsToRead_DF8112></TagsToRead_DF8112>
      <TagsToWriteBeforeGenAC_FF8102></TagsToWriteBeforeGenAC_FF8102>
      <TagsToWriteAfterGenAC_FF8103></TagsToWriteAfterGenAC_FF8103>
      <ProceedToFirstWriteFlag_DF8110>FE</ProceedToFirstWriteFlag_DF8110>
      <DSRequestedOperatorID_9F5C>FFFFFFFFFFFFFFFF</DSRequestedOperatorID_9F5C>
      <DETimeoutValue_DF8127>01F4</DETimeoutValue_DF8127>
      <AppFlowCap_DFAB31>0200000000</AppFlowCap_DFAB31>
      <RR_MinGracePeriod_DF8132>0014</RR_MinGracePeriod_DF8132>
      <RR_MaxGracePeriod_DF8133>0032</RR_MaxGracePeriod_DF8133>
      <RR_ExpTransTimeCAPDU_DF8134>0012</RR_ExpTransTimeCAPDU_DF8134>
      <RR_ExpTransTimeRAPDU_DF8135>0018</RR_ExpTransTimeRAPDU_DF8135>
      <RR_AccuracyThreshold_DF8136>012C</RR_AccuracyThreshold_DF8136>
      <RR_TransTimeMismatchThreshold_DF8137>32</RR_TransTimeMismatchThreshold_DF8137>
      <MerchantCustomData_9F7C></MerchantCustomData_9F7C></MasterCard></Application>
  <Application AID="A0000000042203" KernelID="020000">
    <ASI_DFAB02>01</ASI_DFAB02>
    <AppFlowCap_DFAB03>0000000000</AppFlowCap_DFAB03>
    <SpecialTRXConfig_DFAB05>2120110000000000</SpecialTRXConfig_DFAB05>
    <ChksumEntryPoint_DFAB06>8907D85E</ChksumEntryPoint_DFAB06>
    <ChksumKernel_DFAB07></ChksumKernel_DFAB07>
    <RetapFieldOff_DFAB08>0D</RetapFieldOff_DFAB08>
    <AdditionalTagsTRM_DFAB20></AdditionalTagsTRM_DFAB20>
    <AdditionalTagsCRD_DFAB21>4203</AdditionalTagsCRD_DFAB21>
    <DefaultApplicationName_DFAB22>US Maestro</DefaultApplicationName_DFAB22>
    <MasterCard>
      <TermIdent_9F1C>3132333435363738</TermIdent_9F1C>
      <TerminalCountryCode_9F1A>0840</TerminalCountryCode_9F1A>
      <TerminalType_9F35>22</TerminalType_9F35>
      <AdditionalTerminalCapabilities_9F40>F000F0A001</AdditionalTerminalCapabilities_9F40>
      <MagstripeCVM_aboveLimit_DF811E>10</MagstripeCVM_aboveLimit_DF811E>
      <MagstripeCVM_belowLimit_DF812C>00</MagstripeCVM_belowLimit_DF812C>
      <ChipCVM_aboveLimit_DF8118>40</ChipCVM_aboveLimit_DF8118>
      <ChipCVM_belowLimit_DF8119>08</ChipCVM_belowLimit_DF8119>
      <SecurityCapability_DF811F>08</SecurityCapability_DF811F>
      <CardDataInputCapability_DF8117>E0</CardDataInputCapability_DF8117>
      <FloorLimit_DF8123>000000000000</FloorLimit_DF8123>
      <TransactionLimitNoOnDevice_DF8124>000099999999</TransactionLimitNoOnDevice_DF8124>
      <TransactionLimitOnDevice_DF8125>000000000000</TransactionLimitOnDevice_DF8125>
      <CVMRequiredLimit_DF8126>000000005000</CVMRequiredLimit_DF8126>
      <ChipVersionNumber_9F09>0002000000000000000000000000000000000000</ChipVersionNumber_9F09>
      <MSRVersionNumber_9F6D>0001000000000000000000000000000000000000</MSRVersionNumber_9F6D>
      <KernelConfiguration_DF811B>90</KernelConfiguration_DF811B>
      <TransactionCategoryCode_9F53>52</TransactionCategoryCode_9F53>
      <TACDefault_DF8120>F45084800C</TACDefault_DF8120>
      <TACDenial_DF8121>0000000000</TACDenial_DF8121>
      <TACOnline_DF8122>F45084800C</TACOnline_DF8122>
      <KernelID_DF810C>02</KernelID_DF810C>
      <TerminalRiskManagementData_9F1D>487A800000000000</TerminalRiskManagementData_9F1D>
      <MerchantCategoryCode_9F15>5999</MerchantCategoryCode_9F15>
      <MerchantIdentifier_9F16/>
      <MerchantNameAndLocation_9F4E></MerchantNameAndLocation_9F4E>
      <AcquirerIdentifier_9F01>000000000000</AcquirerIdentifier_9F01>
      <HoldTimeValue_DF8130>0D</HoldTimeValue_DF8130>
      <MessageHoldTime_DF812D>000013</MessageHoldTime_DF812D>
      <TornTransactionLifetime_DF811C>012C</TornTransactionLifetime_DF811C>
      <TornTransactionNumber_DF811D>01</TornTransactionNumber_DF811D>
      <PhoneMessageTable_DF8131>000001000001200000080000080020000004000004002000000100000100200000020000020020000000000000000700</PhoneMessageTable_DF8131>
      <TagsToRead_DF8112></TagsToRead_DF8112>
      <TagsToWriteBeforeGenAC_FF8102></TagsToWriteBeforeGenAC_FF8102>
      <TagsToWriteAfterGenAC_FF8103></TagsToWriteAfterGenAC_FF8103>
      <ProceedToFirstWriteFlag_DF8110>FE</ProceedToFirstWriteFlag_DF8110>
      <DSRequestedOperatorID_9F5C>FFFFFFFFFFFFFFFF</DSRequestedOperatorID_9F5C>
      <DETimeoutValue_DF8127>01F4</DETimeoutValue_DF8127>
      <AppFlowCap_DFAB31>0000000000</AppFlowCap_DFAB31>
      <RR_MinGracePeriod_DF8132>0014</RR_MinGracePeriod_DF8132>
      <RR_MaxGracePeriod_DF8133>0032</RR_MaxGracePeriod_DF8133>
      <RR_ExpTransTimeCAPDU_DF8134>0012</RR_ExpTransTimeCAPDU_DF8134>
      <RR_ExpTransTimeRAPDU_DF8135>0018</RR_ExpTransTimeRAPDU_DF8135>
      <RR_AccuracyThreshold_DF8136>012C</RR_AccuracyThreshold_DF8136>
      <RR_TransTimeMismatchThreshold_DF8137>32</RR_TransTimeMismatchThreshold_DF8137>
      <MerchantCustomData_9F7C></MerchantCustomData_9F7C></MasterCard></Application>
  <Application AID="A00000002501" KernelID="040000">
    <ASI_DFAB02>01</ASI_DFAB02>
    <AppFlowCap_DFAB03>0C03000000</AppFlowCap_DFAB03>
    <SpecialTRXConfig_DFAB05>2120110000000000</SpecialTRXConfig_DFAB05>
    <ChksumEntryPoint_DFAB06>8907D85E</ChksumEntryPoint_DFAB06>
    <ChksumKernel_DFAB07></ChksumKernel_DFAB07>
    <RetapFieldOff_DFAB08>0A</RetapFieldOff_DFAB08>
    <AdditionalTagsTRM_DFAB20></AdditionalTagsTRM_DFAB20>
    <AdditionalTagsCRD_DFAB21></AdditionalTagsCRD_DFAB21>
    <DefaultApplicationName_DFAB22>Amex</DefaultApplicationName_DFAB22>
    <AmericanExpress>
      <TermIdent_9F1C>3132333435363738</TermIdent_9F1C>
      <TerminalCountryCode_9F1A>0840</TerminalCountryCode_9F1A>
      <TerminalType_9F35>22</TerminalType_9F35>
      <AmexContactlessReaderCapabilities_9F6D>C0</AmexContactlessReaderCapabilities_9F6D>
      <AmexTerminalTransactionCapabilities_9F6E>D8F00000</AmexTerminalTransactionCapabilities_9F6E>
      <TerminalCapabilities_9F33>E0E888</TerminalCapabilities_9F33>
      <AdditionalTerminalCapabilities_9F40>F000F0A001</AdditionalTerminalCapabilities_9F40>
      <VersionNumber_9F09>0001000000000000000000000000000000000000</VersionNumber_9F09>
      <MerchantCategoryCode_9F15>5999</MerchantCategoryCode_9F15>
      <MerchantIdentifier_9F16/>
      <MerchantNameAndLocation_9F4E></MerchantNameAndLocation_9F4E>
      <AcquirerIdentifier_9F01>000000000000</AcquirerIdentifier_9F01>
      <TecSupport_DFAB30>03</TecSupport_DFAB30>
      <AppFlowCap_DFAB31>0100000000</AppFlowCap_DFAB31>
      <ContactlessFloorLimit_DFAB40>000000000000</ContactlessFloorLimit_DFAB40>
      <ContactlessTransactionLimit_DFAB41>000000001500</ContactlessTransactionLimit_DFAB41>
      <ContactlessCVMRequiredLimit_DFAB42>000000001000</ContactlessCVMRequiredLimit_DFAB42>
      <TACDefault_DFAB43>DC50FC9800</TACDefault_DFAB43>
      <TACDenial_DFAB44>0010000000</TACDenial_DFAB44>
      <TACOnline_DFAB45>DE00FC9800</TACOnline_DFAB45>
      <UnpredictableNumberRange_DFAB52>3C</UnpredictableNumberRange_DFAB52></AmericanExpress></Application>
  <Application AID="A0000000651010" KernelID="050000">
    <ASI_DFAB02>01</ASI_DFAB02>
    <AppFlowCap_DFAB03>0C03000000</AppFlowCap_DFAB03>
    <SpecialTRXConfig_DFAB05>2120110000000000</SpecialTRXConfig_DFAB05>
    <ChksumEntryPoint_DFAB06>8907D85E</ChksumEntryPoint_DFAB06>
    <ChksumKernel_DFAB07></ChksumKernel_DFAB07>
    <RetapFieldOff_DFAB08>0A</RetapFieldOff_DFAB08>
    <AdditionalTagsTRM_DFAB20></AdditionalTagsTRM_DFAB20>
    <AdditionalTagsCRD_DFAB21></AdditionalTagsCRD_DFAB21>
    <DefaultApplicationName_DFAB22>JCB</DefaultApplicationName_DFAB22>
    <JCB>
      <TermIdent_9F1C>3132333435363738</TermIdent_9F1C>
      <TerminalCountryCode_9F1A>0840</TerminalCountryCode_9F1A>
      <TerminalType_9F35>22</TerminalType_9F35>
      <TerminalInterchangeProfile_9F53>730000</TerminalInterchangeProfile_9F53>
      <MerchantCategoryCode_9F15>5999</MerchantCategoryCode_9F15>
      <MerchantNameAndLocation_9F4E></MerchantNameAndLocation_9F4E>
      <AcquirerIdentifier_9F01>000000000000</AcquirerIdentifier_9F01>
      <AppFlowCap_DFAB31>0000000000</AppFlowCap_DFAB31>
      <ContactlessFloorLimit_DFAB40>000000000000</ContactlessFloorLimit_DFAB40>
      <ContactlessTransactionLimit_DFAB41>000001000000</ContactlessTransactionLimit_DFAB41>
      <ContactlessCVMRequiredLimit_DFAB42>000000002501</ContactlessCVMRequiredLimit_DFAB42>
      <TACDefault_DFAB43>9040008000</TACDefault_DFAB43>
      <TACDenial_DFAB44>0410000000</TACDenial_DFAB44>
      <TACOnline_DFAB45>9060009000</TACOnline_DFAB45>
      <RiskManagementThreshold_DFAB46>000000000000</RiskManagementThreshold_DFAB46>
      <RiskManagementTargetPercentage_DFAB47>00</RiskManagementTargetPercentage_DFAB47>
      <RiskManagementMaximumTargetPercentage_DFAB48>00</RiskManagementMaximumTargetPercentage_DFAB48>
      <CombinationOptions_DFAB4B>3B00</CombinationOptions_DFAB4B>
      <RemovalTimeout_DFAB4C>0000</RemovalTimeout_DFAB4C>
      <CL_TXN_Limit_ODCVM_DFAB5B>000001000000</CL_TXN_Limit_ODCVM_DFAB5B></JCB></Application>
  <Application AID="A0000001523010" KernelID="060000">
    <ASI_DFAB02>01</ASI_DFAB02>
    <AppFlowCap_DFAB03>0C03000000</AppFlowCap_DFAB03>
    <SpecialTRXConfig_DFAB05>2120110000000000</SpecialTRXConfig_DFAB05>
    <ChksumEntryPoint_DFAB06>8907D85E</ChksumEntryPoint_DFAB06>
    <ChksumKernel_DFAB07></ChksumKernel_DFAB07>
    <RetapFieldOff_DFAB08>0A</RetapFieldOff_DFAB08>
    <AdditionalTagsTRM_DFAB20></AdditionalTagsTRM_DFAB20>
    <AdditionalTagsCRD_DFAB21></AdditionalTagsCRD_DFAB21>
    <DefaultApplicationName_DFAB22>Discover</DefaultApplicationName_DFAB22>
    <Discover>
      <TermIdent_9F1C>3132333435363738</TermIdent_9F1C>
      <TerminalCountryCode_9F1A>0840</TerminalCountryCode_9F1A>
      <TerminalType_9F35>22</TerminalType_9F35>
      <TerminalTransactionQualifier_9F66>36208000</TerminalTransactionQualifier_9F66>
      <TerminalCapabilities_9F33>E0F8C8</TerminalCapabilities_9F33>
      <AdditionalTerminalCapabilities_9F40>F000F0A001</AdditionalTerminalCapabilities_9F40>
      <VersionNumber_9F09>0001000000000000000000000000000000000000</VersionNumber_9F09>
      <MerchantCategoryCode_9F15>5999</MerchantCategoryCode_9F15>
      <TecSupport_DFAB30>01</TecSupport_DFAB30>
      <AppFlowCap_DFAB31>0000000000</AppFlowCap_DFAB31>
      <ContactlessFloorLimit_DFAB40>000000000000</ContactlessFloorLimit_DFAB40>
      <ContactlessTransactionLimit_DFAB41>000000002001</ContactlessTransactionLimit_DFAB41>
      <ContactlessCVMRequiredLimit_DFAB42>000000000901</ContactlessCVMRequiredLimit_DFAB42>
      <DataContainerReadIds_DFAB58></DataContainerReadIds_DFAB58>
      <DataContainerReadRanges_DFAB59></DataContainerReadRanges_DFAB59></Discover></Application>
  <Application AID="A0000001524010" KernelID="060000">
    <ASI_DFAB02>01</ASI_DFAB02>
    <AppFlowCap_DFAB03>0000000000</AppFlowCap_DFAB03>
    <SpecialTRXConfig_DFAB05>2120110000000000</SpecialTRXConfig_DFAB05>
    <ChksumEntryPoint_DFAB06>8907D85E</ChksumEntryPoint_DFAB06>
    <ChksumKernel_DFAB07></ChksumKernel_DFAB07>
    <RetapFieldOff_DFAB08>0D</RetapFieldOff_DFAB08>
    <AdditionalTagsTRM_DFAB20></AdditionalTagsTRM_DFAB20>
    <AdditionalTagsCRD_DFAB21>4203</AdditionalTagsCRD_DFAB21>
    <DefaultApplicationName_DFAB22>Discover</DefaultApplicationName_DFAB22>
    <Discover>
      <TermIdent_9F1C>3132333435363738</TermIdent_9F1C>
      <TerminalCountryCode_9F1A>0840</TerminalCountryCode_9F1A>
      <TerminalType_9F35>22</TerminalType_9F35>
      <TerminalTransactionQualifier_9F66>36204000</TerminalTransactionQualifier_9F66>
      <TerminalCapabilities_9F33>E06808</TerminalCapabilities_9F33>
      <AdditionalTerminalCapabilities_9F40>F000F0A001</AdditionalTerminalCapabilities_9F40>
      <VersionNumber_9F09>0001000000000000000000000000000000000000</VersionNumber_9F09>
      <MerchantCategoryCode_9F15>5999</MerchantCategoryCode_9F15>
      <TecSupport_DFAB30>01</TecSupport_DFAB30>
      <AppFlowCap_DFAB31>0000000000</AppFlowCap_DFAB31>
      <ContactlessFloorLimit_DFAB40>000000000000</ContactlessFloorLimit_DFAB40>
      <ContactlessTransactionLimit_DFAB41>000099999999</ContactlessTransactionLimit_DFAB41>
      <ContactlessCVMRequiredLimit_DFAB42>000000005000</ContactlessCVMRequiredLimit_DFAB42>
      <DataContainerReadIds_DFAB58></DataContainerReadIds_DFAB58>
      <DataContainerReadRanges_DFAB59></DataContainerReadRanges_DFAB59></Discover></Application>
  <Application AID="A000000333010101" KernelID="070000">
    <ASI_DFAB02>01</ASI_DFAB02>
    <AppFlowCap_DFAB03>0C03000000</AppFlowCap_DFAB03>
    <SpecialTRXConfig_DFAB05>2120110000000000</SpecialTRXConfig_DFAB05>
    <ChksumEntryPoint_DFAB06>8907D85E</ChksumEntryPoint_DFAB06>
    <ChksumKernel_DFAB07></ChksumKernel_DFAB07>
    <RetapFieldOff_DFAB08>0A</RetapFieldOff_DFAB08>
    <AdditionalTagsTRM_DFAB20></AdditionalTagsTRM_DFAB20>
    <AdditionalTagsCRD_DFAB21></AdditionalTagsCRD_DFAB21>
    <DefaultApplicationName_DFAB22>Union Pay</DefaultApplicationName_DFAB22>
    <ChinaUnionPay>
      <TermIdent_9F1C>3132333435363738</TermIdent_9F1C>
      <TerminalCountryCode_9F1A>0840</TerminalCountryCode_9F1A>
      <TerminalType_9F35>22</TerminalType_9F35>
      <TerminalTransactionQualifier_9F66>36004080</TerminalTransactionQualifier_9F66>
      <TerminalCapabilities_9F33>E0F8C8</TerminalCapabilities_9F33>
      <AdditionalTerminalCapabilities_9F40>F000F0A001</AdditionalTerminalCapabilities_9F40>
      <VersionNumber_9F09>0020000000000000000000000000000000000000</VersionNumber_9F09>
      <MerchantCategoryCode_9F15>5999</MerchantCategoryCode_9F15>
      <MerchantIdentifier_9F16/>
      <MerchantNameAndLocation_9F4E></MerchantNameAndLocation_9F4E>
      <TecSupport_DFAB30>01</TecSupport_DFAB30>
      <AppFlowCap_DFAB31>0400000000</AppFlowCap_DFAB31>
      <ContactlessFloorLimit_DFAB40>000000000000</ContactlessFloorLimit_DFAB40>
      <ContactlessTransactionLimit_DFAB41>000000002000</ContactlessTransactionLimit_DFAB41>
      <ContactlessCVMRequiredLimit_DFAB42>000000000900</ContactlessCVMRequiredLimit_DFAB42></ChinaUnionPay></Application>
  <Application AID="A000000333010102" KernelID="070000">
    <ASI_DFAB02>01</ASI_DFAB02>
    <AppFlowCap_DFAB03>0C03000000</AppFlowCap_DFAB03>
    <SpecialTRXConfig_DFAB05>2120110000000000</SpecialTRXConfig_DFAB05>
    <ChksumEntryPoint_DFAB06>8907D85E</ChksumEntryPoint_DFAB06>
    <ChksumKernel_DFAB07></ChksumKernel_DFAB07>
    <RetapFieldOff_DFAB08>0A</RetapFieldOff_DFAB08>
    <AdditionalTagsTRM_DFAB20></AdditionalTagsTRM_DFAB20>
    <AdditionalTagsCRD_DFAB21></AdditionalTagsCRD_DFAB21>
    <DefaultApplicationName_DFAB22>Union Pay</DefaultApplicationName_DFAB22>
    <ChinaUnionPay>
      <TermIdent_9F1C>3132333435363738</TermIdent_9F1C>
      <TerminalCountryCode_9F1A>0840</TerminalCountryCode_9F1A>
      <TerminalType_9F35>22</TerminalType_9F35>
      <TerminalTransactionQualifier_9F66>36004080</TerminalTransactionQualifier_9F66>
      <TerminalCapabilities_9F33>E0F8C8</TerminalCapabilities_9F33>
      <AdditionalTerminalCapabilities_9F40>F000F0A001</AdditionalTerminalCapabilities_9F40>
      <VersionNumber_9F09>0020000000000000000000000000000000000000</VersionNumber_9F09>
      <MerchantCategoryCode_9F15>5999</MerchantCategoryCode_9F15>
      <MerchantIdentifier_9F16/>
      <MerchantNameAndLocation_9F4E></MerchantNameAndLocation_9F4E>
      <TecSupport_DFAB30>01</TecSupport_DFAB30>
      <AppFlowCap_DFAB31>0400000000</AppFlowCap_DFAB31>
      <ContactlessFloorLimit_DFAB40>000000000000</ContactlessFloorLimit_DFAB40>
      <ContactlessTransactionLimit_DFAB41>000000002000</ContactlessTransactionLimit_DFAB41>
      <ContactlessCVMRequiredLimit_DFAB42>000000000900</ContactlessCVMRequiredLimit_DFAB42></ChinaUnionPay></Application>
  <Application AID="A000000333010103" KernelID="070000">
    <ASI_DFAB02>01</ASI_DFAB02>
    <AppFlowCap_DFAB03>0C03000000</AppFlowCap_DFAB03>
    <SpecialTRXConfig_DFAB05>2120110000000000</SpecialTRXConfig_DFAB05>
    <ChksumEntryPoint_DFAB06>8907D85E</ChksumEntryPoint_DFAB06>
    <ChksumKernel_DFAB07></ChksumKernel_DFAB07>
    <RetapFieldOff_DFAB08>0A</RetapFieldOff_DFAB08>
    <AdditionalTagsTRM_DFAB20></AdditionalTagsTRM_DFAB20>
    <AdditionalTagsCRD_DFAB21></AdditionalTagsCRD_DFAB21>
    <DefaultApplicationName_DFAB22>Union Pay</DefaultApplicationName_DFAB22>
    <ChinaUnionPay>
      <TermIdent_9F1C>3132333435363738</TermIdent_9F1C>
      <TerminalCountryCode_9F1A>0840</TerminalCountryCode_9F1A>
      <TerminalType_9F35>22</TerminalType_9F35>
      <TerminalTransactionQualifier_9F66>36004080</TerminalTransactionQualifier_9F66>
      <TerminalCapabilities_9F33>E0F8C8</TerminalCapabilities_9F33>
      <AdditionalTerminalCapabilities_9F40>F000F0A001</AdditionalTerminalCapabilities_9F40>
      <VersionNumber_9F09>0020000000000000000000000000000000000000</VersionNumber_9F09>
      <MerchantCategoryCode_9F15>5999</MerchantCategoryCode_9F15>
      <MerchantIdentifier_9F16/>
      <MerchantNameAndLocation_9F4E></MerchantNameAndLocation_9F4E>
      <TecSupport_DFAB30>01</TecSupport_DFAB30>
      <AppFlowCap_DFAB31>0400000000</AppFlowCap_DFAB31>
      <ContactlessFloorLimit_DFAB40>000000000000</ContactlessFloorLimit_DFAB40>
      <ContactlessTransactionLimit_DFAB41>000000002000</ContactlessTransactionLimit_DFAB41>
      <ContactlessCVMRequiredLimit_DFAB42>000000000900</ContactlessCVMRequiredLimit_DFAB42></ChinaUnionPay></Application>
  <Application AID="A000000333010106" KernelID="070000">
    <ASI_DFAB02>01</ASI_DFAB02>
    <AppFlowCap_DFAB03>0C03000000</AppFlowCap_DFAB03>
    <SpecialTRXConfig_DFAB05>2120110000000000</SpecialTRXConfig_DFAB05>
    <ChksumEntryPoint_DFAB06>8907D85E</ChksumEntryPoint_DFAB06>
    <ChksumKernel_DFAB07></ChksumKernel_DFAB07>
    <RetapFieldOff_DFAB08>0A</RetapFieldOff_DFAB08>
    <AdditionalTagsTRM_DFAB20></AdditionalTagsTRM_DFAB20>
    <AdditionalTagsCRD_DFAB21></AdditionalTagsCRD_DFAB21>
    <DefaultApplicationName_DFAB22>Union Pay</DefaultApplicationName_DFAB22>
    <ChinaUnionPay>
      <TermIdent_9F1C>3132333435363738</TermIdent_9F1C>
      <TerminalCountryCode_9F1A>0840</TerminalCountryCode_9F1A>
      <TerminalType_9F35>22</TerminalType_9F35>
      <TerminalTransactionQualifier_9F66>36004080</TerminalTransactionQualifier_9F66>
      <TerminalCapabilities_9F33>E0F8C8</TerminalCapabilities_9F33>
      <AdditionalTerminalCapabilities_9F40>F000F0A001</AdditionalTerminalCapabilities_9F40>
      <VersionNumber_9F09>0020000000000000000000000000000000000000</VersionNumber_9F09>
      <MerchantCategoryCode_9F15>5999</MerchantCategoryCode_9F15>
      <MerchantIdentifier_9F16/>
      <MerchantNameAndLocation_9F4E></MerchantNameAndLocation_9F4E>
      <TecSupport_DFAB30>01</TecSupport_DFAB30>
      <AppFlowCap_DFAB31>0400000000</AppFlowCap_DFAB31>
      <ContactlessFloorLimit_DFAB40>000000000000</ContactlessFloorLimit_DFAB40>
      <ContactlessTransactionLimit_DFAB41>000000002000</ContactlessTransactionLimit_DFAB41>
      <ContactlessCVMRequiredLimit_DFAB42>000000000900</ContactlessCVMRequiredLimit_DFAB42></ChinaUnionPay></Application>
  <Application AID="A000000333010108" KernelID="070000">
    <ASI_DFAB02>01</ASI_DFAB02>
    <AppFlowCap_DFAB03>0000000000</AppFlowCap_DFAB03>
    <SpecialTRXConfig_DFAB05>2120110000000000</SpecialTRXConfig_DFAB05>
    <ChksumEntryPoint_DFAB06>8907D85E</ChksumEntryPoint_DFAB06>
    <ChksumKernel_DFAB07></ChksumKernel_DFAB07>
    <RetapFieldOff_DFAB08>0D</RetapFieldOff_DFAB08>
    <AdditionalTagsTRM_DFAB20></AdditionalTagsTRM_DFAB20>
    <AdditionalTagsCRD_DFAB21>4203</AdditionalTagsCRD_DFAB21>
    <DefaultApplicationName_DFAB22>Union Pay</DefaultApplicationName_DFAB22>
    <ChinaUnionPay>
      <TermIdent_9F1C>3132333435363738</TermIdent_9F1C>
      <TerminalCountryCode_9F1A>0156</TerminalCountryCode_9F1A>
      <TerminalType_9F35>22</TerminalType_9F35>
      <TerminalTransactionQualifier_9F66>36004080</TerminalTransactionQualifier_9F66>
      <TerminalCapabilities_9F33>E068C8</TerminalCapabilities_9F33>
      <AdditionalTerminalCapabilities_9F40>F000F0A001</AdditionalTerminalCapabilities_9F40>
      <VersionNumber_9F09>0020000000000000000000000000000000000000</VersionNumber_9F09>
      <MerchantCategoryCode_9F15>5999</MerchantCategoryCode_9F15>
      <MerchantIdentifier_9F16/>
      <MerchantNameAndLocation_9F4E></MerchantNameAndLocation_9F4E>
      <TecSupport_DFAB30>01</TecSupport_DFAB30>
      <AppFlowCap_DFAB31>0400000000</AppFlowCap_DFAB31>
      <ContactlessFloorLimit_DFAB40>000000000000</ContactlessFloorLimit_DFAB40>
      <ContactlessTransactionLimit_DFAB41>000099999999</ContactlessTransactionLimit_DFAB41>
      <ContactlessCVMRequiredLimit_DFAB42>000000005000</ContactlessCVMRequiredLimit_DFAB42></ChinaUnionPay></Application>
  <Application AID="A0000002771010" KernelID="100000">
    <ASI_DFAB02>01</ASI_DFAB02>
    <AppFlowCap_DFAB03>0000000000</AppFlowCap_DFAB03>
    <SpecialTRXConfig_DFAB05>2120110000000000</SpecialTRXConfig_DFAB05>
    <ChksumEntryPoint_DFAB06>8907D85E</ChksumEntryPoint_DFAB06>
    <ChksumKernel_DFAB07></ChksumKernel_DFAB07>
    <RetapFieldOff_DFAB08>0D</RetapFieldOff_DFAB08>
    <AdditionalTagsTRM_DFAB20></AdditionalTagsTRM_DFAB20>
    <AdditionalTagsCRD_DFAB21>4203</AdditionalTagsCRD_DFAB21>
    <DefaultApplicationName_DFAB22>Interac</DefaultApplicationName_DFAB22>
    <Interac>
      <TermIdent_9F1C>3132333435363738</TermIdent_9F1C>
      <TerminalCountryCode_9F1A>0840</TerminalCountryCode_9F1A>
      <TerminalType_9F35>22</TerminalType_9F35>
      <TerminalCapabilities_9F33>E028C8</TerminalCapabilities_9F33>
      <AdditionalTerminalCapabilities_9F40>F000F0A001</AdditionalTerminalCapabilities_9F40>
      <ContactlessFloorLimit_9F5F>000000000000</ContactlessFloorLimit_9F5F>
      <MerchantTypeIndicator_9F58>01</MerchantTypeIndicator_9F58>
      <TerminalTransactionInformation_9F59>D8C700</TerminalTransactionInformation_9F59>
      <TerminalTransactionType_9F5A>00</TerminalTransactionType_9F5A>
      <TerminalOptionStatus_9F5E>E000</TerminalOptionStatus_9F5E>
      <ReceiptRequiredLimit_9F5D>000000005000</ReceiptRequiredLimit_9F5D>
      <TryAgainLimit_DF6D>02</TryAgainLimit_DF6D>
      <VersionNumber_9F09>0002000200000000000000000000000000000000</VersionNumber_9F09>
      <MerchantCategoryCode_9F15>5999</MerchantCategoryCode_9F15>
      <MerchantIdentifier_9F16/>
      <MerchantNameAndLocation_9F4E></MerchantNameAndLocation_9F4E>
      <AcquirerIdentifier_9F01>000000000000</AcquirerIdentifier_9F01>
      <AppFlowCap_DFAB31>0300000000</AppFlowCap_DFAB31>
      <ContactlessTransactionLimit_DFAB41>000000008000</ContactlessTransactionLimit_DFAB41>
      <ContactlessCVMRequiredLimit_DFAB42>000000000000</ContactlessCVMRequiredLimit_DFAB42>
      <TACDefault_DFAB43>FC78FCF800</TACDefault_DFAB43>
      <TACDenial_DFAB44>0000000000</TACDenial_DFAB44>
      <TACOnline_DFAB45>FC78FCF800</TACOnline_DFAB45>
      <RiskManagementThreshold_DFAB46>000000000000</RiskManagementThreshold_DFAB46>
      <RiskManagementTargetPercentage_DFAB47>99</RiskManagementTargetPercentage_DFAB47>
      <RiskManagementMaximumTargetPercentage_DFAB48>99</RiskManagementMaximumTargetPercentage_DFAB48></Interac></Application>
  <Application AID="A00000038410" KernelID="110000">
    <ASI_DFAB02>01</ASI_DFAB02>
    <AppFlowCap_DFAB03>0C03000000</AppFlowCap_DFAB03>
    <SpecialTRXConfig_DFAB05>2120110000000000</SpecialTRXConfig_DFAB05>
    <ChksumEntryPoint_DFAB06>8907D85E</ChksumEntryPoint_DFAB06>
    <ChksumKernel_DFAB07></ChksumKernel_DFAB07>
    <RetapFieldOff_DFAB08>0A</RetapFieldOff_DFAB08>
    <AdditionalTagsTRM_DFAB20></AdditionalTagsTRM_DFAB20>
    <AdditionalTagsCRD_DFAB21></AdditionalTagsCRD_DFAB21>
    <DefaultApplicationName_DFAB22>EPAL saving</DefaultApplicationName_DFAB22>
    <EPAL>
      <TermIdent_9F1C>3132333435363738</TermIdent_9F1C>
      <TerminalCountryCode_9F1A>0840</TerminalCountryCode_9F1A>
      <TerminalType_9F35>22</TerminalType_9F35>
      <TerminalCapabilities_9F33>E04808</TerminalCapabilities_9F33>
      <AdditionalTerminalCapabilities_9F40>F000F0A001</AdditionalTerminalCapabilities_9F40>
      <VersionNumber_9F09>0100000000000000000000000000000000000000</VersionNumber_9F09>
      <MerchantCategoryCode_9F15>5999</MerchantCategoryCode_9F15>
      <MerchantIdentifier_9F16/>
      <MerchantNameAndLocation_9F4E></MerchantNameAndLocation_9F4E>
      <AcquirerIdentifier_9F01>000000000000</AcquirerIdentifier_9F01>
      <TerminalTransactionQualifier_9F66>00004000</TerminalTransactionQualifier_9F66>
      <AppFlowCap_DFAB31>0000000000</AppFlowCap_DFAB31>
      <ContactlessFloorLimit_DFAB40>000000000000</ContactlessFloorLimit_DFAB40>
      <ContactlessTransactionLimit_DFAB41>000000010000</ContactlessTransactionLimit_DFAB41>
      <TACDefault_DFAB43>FFFFFFFFFF</TACDefault_DFAB43>
      <TACDenial_DFAB44>0400000000</TACDenial_DFAB44>
      <TACOnline_DFAB45>FC509C9800</TACOnline_DFAB45>
      <CtlsTransactionLimitCash_DFAB4A>000000010000</CtlsTransactionLimitCash_DFAB4A></EPAL></Application>
  <Application AID="A00000038420" KernelID="110000">
    <ASI_DFAB02>01</ASI_DFAB02>
    <AppFlowCap_DFAB03>0C03000000</AppFlowCap_DFAB03>
    <SpecialTRXConfig_DFAB05>2120110000000000</SpecialTRXConfig_DFAB05>
    <ChksumEntryPoint_DFAB06>8907D85E</ChksumEntryPoint_DFAB06>
    <ChksumKernel_DFAB07></ChksumKernel_DFAB07>
    <RetapFieldOff_DFAB08>0A</RetapFieldOff_DFAB08>
    <AdditionalTagsTRM_DFAB20></AdditionalTagsTRM_DFAB20>
    <AdditionalTagsCRD_DFAB21></AdditionalTagsCRD_DFAB21>
    <DefaultApplicationName_DFAB22>EPAL cheque</DefaultApplicationName_DFAB22>
    <EPAL>
      <TermIdent_9F1C>3132333435363738</TermIdent_9F1C>
      <TerminalCountryCode_9F1A>0840</TerminalCountryCode_9F1A>
      <TerminalType_9F35>22</TerminalType_9F35>
      <TerminalCapabilities_9F33>E04808</TerminalCapabilities_9F33>
      <AdditionalTerminalCapabilities_9F40>F000F0A001</AdditionalTerminalCapabilities_9F40>
      <VersionNumber_9F09>0100000000000000000000000000000000000000</VersionNumber_9F09>
      <MerchantCategoryCode_9F15>5999</MerchantCategoryCode_9F15>
      <MerchantIdentifier_9F16/>
      <MerchantNameAndLocation_9F4E></MerchantNameAndLocation_9F4E>
      <AcquirerIdentifier_9F01>000000000000</AcquirerIdentifier_9F01>
      <TerminalTransactionQualifier_9F66>00004000</TerminalTransactionQualifier_9F66>
      <AppFlowCap_DFAB31>0000000000</AppFlowCap_DFAB31>
      <ContactlessFloorLimit_DFAB40>000000000000</ContactlessFloorLimit_DFAB40>
      <ContactlessTransactionLimit_DFAB41>000000010000</ContactlessTransactionLimit_DFAB41>
      <TACDefault_DFAB43>FFFFFFFFFF</TACDefault_DFAB43>
      <TACDenial_DFAB44>0400000000</TACDenial_DFAB44>
      <TACOnline_DFAB45>FC509C9800</TACOnline_DFAB45>
      <CtlsTransactionLimitCash_DFAB4A>000000010000</CtlsTransactionLimitCash_DFAB4A></EPAL></Application>
  <Application AID="A0000003591010028001" KernelID="2A0000">
    <ASI_DFAB02>01</ASI_DFAB02>
    <AppFlowCap_DFAB03>0C03000000</AppFlowCap_DFAB03>
    <SpecialTRXConfig_DFAB05>2120110000000000</SpecialTRXConfig_DFAB05>
    <ChksumEntryPoint_DFAB06>8907D85E</ChksumEntryPoint_DFAB06>
    <ChksumKernel_DFAB07></ChksumKernel_DFAB07>
    <RetapFieldOff_DFAB08>0A</RetapFieldOff_DFAB08>
    <AdditionalTagsTRM_DFAB20></AdditionalTagsTRM_DFAB20>
    <AdditionalTagsCRD_DFAB21></AdditionalTagsCRD_DFAB21>
    <DefaultApplicationName_DFAB22>girocard</DefaultApplicationName_DFAB22>
    <girocard>
      <TermIdent_9F1C>3132333435363738</TermIdent_9F1C>
      <TerminalCountryCode_9F1A>0840</TerminalCountryCode_9F1A>
      <TerminalType_9F35>22</TerminalType_9F35>
      <AdditionalTerminalCapabilities_9F40>F000F0A001</AdditionalTerminalCapabilities_9F40>
      <MagstripeCVM_aboveLimit_DF811E>10</MagstripeCVM_aboveLimit_DF811E>
      <MagstripeCVM_belowLimit_DF812C>00</MagstripeCVM_belowLimit_DF812C>
      <ChipCVM_aboveLimit_DF8118>50</ChipCVM_aboveLimit_DF8118>
      <ChipCVM_belowLimit_DF8119>58</ChipCVM_belowLimit_DF8119>
      <SecurityCapability_DF811F>08</SecurityCapability_DF811F>
      <CardDataInputCapability_DF8117>20</CardDataInputCapability_DF8117>
      <FloorLimit_DF8123>000000000000</FloorLimit_DF8123>
      <TransactionLimitNoOnDevice_DF8124>999999999999</TransactionLimitNoOnDevice_DF8124>
      <TransactionLimitOnDevice_DF8125>999999999999</TransactionLimitOnDevice_DF8125>
      <CVMRequiredLimit_DF8126>000000002000</CVMRequiredLimit_DF8126>
      <ChipVersionNumber_9F09>0002000000000000000000000000000000000000</ChipVersionNumber_9F09>
      <MSRVersionNumber_9F6D>0001000000000000000000000000000000000000</MSRVersionNumber_9F6D>
      <KernelConfiguration_DF811B>A0</KernelConfiguration_DF811B>
      <TransactionCategoryCode_9F53>52</TransactionCategoryCode_9F53>
      <TACDefault_DF8120>FC509C8800</TACDefault_DF8120>
      <TACDenial_DF8121>0000000000</TACDenial_DF8121>
      <TACOnline_DF8122>FC509C8800</TACOnline_DF8122>
      <KernelID_DF810C>2A</KernelID_DF810C>
      <TerminalRiskManagementData_9F1D>DC50800000000000</TerminalRiskManagementData_9F1D>
      <MerchantCategoryCode_9F15>5999</MerchantCategoryCode_9F15>
      <MerchantIdentifier_9F16/>
      <MerchantNameAndLocation_9F4E></MerchantNameAndLocation_9F4E>
      <AcquirerIdentifier_9F01>000000000000</AcquirerIdentifier_9F01>
      <HoldTimeValue_DF8130>00</HoldTimeValue_DF8130>
      <MessageHoldTime_DF812D>000000</MessageHoldTime_DF812D>
      <TornTransactionLifetime_DF811C>0078</TornTransactionLifetime_DF811C>
      <TornTransactionNumber_DF811D>01</TornTransactionNumber_DF811D>
      <PhoneMessageTable_DF8131>0000000000000000</PhoneMessageTable_DF8131>
      <TagsToRead_DF8112></TagsToRead_DF8112>
      <TagsToWriteBeforeGenAC_FF8102></TagsToWriteBeforeGenAC_FF8102>
      <TagsToWriteAfterGenAC_FF8103></TagsToWriteAfterGenAC_FF8103>
      <ProceedToFirstWriteFlag_DF8110>FE</ProceedToFirstWriteFlag_DF8110>
      <DSRequestedOperatorID_9F5C>FFFFFFFFFFFFFFFF</DSRequestedOperatorID_9F5C>
      <DETimeoutValue_DF8127>01F4</DETimeoutValue_DF8127>
      <AppFlowCap_DFAB31>0200000000</AppFlowCap_DFAB31>
      <RR_MinGracePeriod_DF8132>0014</RR_MinGracePeriod_DF8132>
      <RR_MaxGracePeriod_DF8133>0032</RR_MaxGracePeriod_DF8133>
      <RR_ExpTransTimeCAPDU_DF8134>0012</RR_ExpTransTimeCAPDU_DF8134>
      <RR_ExpTransTimeRAPDU_DF8135>0018</RR_ExpTransTimeRAPDU_DF8135>
      <RR_AccuracyThreshold_DF8136>012C</RR_AccuracyThreshold_DF8136>
      <RR_TransTimeMismatchThreshold_DF8137>50</RR_TransTimeMismatchThreshold_DF8137>
      <MerchantCustomData_9F7C></MerchantCustomData_9F7C></girocard></Application></ApplicationData>
